CedarBackup3/__init__.py
CedarBackup3/action.py
CedarBackup3/cli.py
CedarBackup3/config.py
CedarBackup3/customize.py
CedarBackup3/filesystem.py
CedarBackup3/image.py
CedarBackup3/knapsack.py
CedarBackup3/peer.py
CedarBackup3/release.py
CedarBackup3/scripts.py
CedarBackup3/testutil.py
CedarBackup3/util.py
CedarBackup3/writer.py
CedarBackup3/xmlutil.py
CedarBackup3/actions/__init__.py
CedarBackup3/actions/collect.py
CedarBackup3/actions/constants.py
CedarBackup3/actions/initialize.py
CedarBackup3/actions/purge.py
CedarBackup3/actions/rebuild.py
CedarBackup3/actions/stage.py
CedarBackup3/actions/store.py
CedarBackup3/actions/util.py
CedarBackup3/actions/validate.py
CedarBackup3/extend/__init__.py
CedarBackup3/extend/amazons3.py
CedarBackup3/extend/capacity.py
CedarBackup3/extend/encrypt.py
CedarBackup3/extend/mbox.py
CedarBackup3/extend/mysql.py
CedarBackup3/extend/postgresql.py
CedarBackup3/extend/split.py
CedarBackup3/extend/subversion.py
CedarBackup3/extend/sysinfo.py
CedarBackup3/tools/__init__.py
CedarBackup3/tools/amazons3.py
CedarBackup3/tools/span.py
CedarBackup3/writers/__init__.py
CedarBackup3/writers/cdwriter.py
CedarBackup3/writers/dvdwriter.py
CedarBackup3/writers/util.py
cedar_backup3-3.12.0.dist-info/METADATA
cedar_backup3-3.12.0.dist-info/WHEEL
cedar_backup3-3.12.0.dist-info/entry_points.txt
cedar_backup3-3.12.0.dist-info/licenses/LICENSE
cedar_backup3-3.12.0.dist-info/licenses/NOTICE
cedar_backup3-3.12.0.dist-info/RECORD
