Metadata-Version: 2.4
Name: cedar-backup3
Version: 3.12.0
Summary: Implements local and remote backups to CD/DVD and Amazon S3
Project-URL: Homepage, https://pypi.org/project/cedar-backup3/
Project-URL: Repository, https://github.com/pronovic/cedar-backup3
Project-URL: Changelog, https://github.com/pronovic/cedar-backup3/releases
Project-URL: Documentation, https://cedar-backup3.readthedocs.io/en/stable/
Project-URL: Issues, https://github.com/pronovic/cedar-backup3/issues
Author-email: "Kenneth J. Pronovici" <pronovic@ieee.org>
License-Expression: GPL-2.0-only
License-File: LICENSE
License-File: NOTICE
Keywords: backup,local,remote,scp
Classifier: Development Status :: 5 - Production/Stable
Classifier: Environment :: Console
Classifier: Intended Audience :: System Administrators
Classifier: Natural Language :: English
Classifier: Operating System :: OS Independent
Classifier: Programming Language :: Python :: 3
Classifier: Programming Language :: Python :: 3.11
Classifier: Programming Language :: Python :: 3.12
Classifier: Programming Language :: Python :: 3.13
Classifier: Programming Language :: Python :: 3.14
Classifier: Topic :: Software Development :: Libraries
Classifier: Topic :: System :: Archiving :: Backup
Classifier: Topic :: Utilities
Requires-Python: <4,>=3.11
Requires-Dist: chardet<6.0.0,>=5.2.0
Provides-Extra: docs
Requires-Dist: sphinx-autoapi<4.0.0,>=3.3.3; extra == 'docs'
Requires-Dist: sphinx<9.0.0,>=8.1.3; extra == 'docs'
